[
    {
        "id": 1,
        "firstname": "Andrew",
        "lastname": "Joseph",
        "M_name": "Vendor",
        "email": "andrew@gmail.com",
        "major": "Computer",
        "address": "KTM",
        "phone_number": 9819643934,
        "person_id": 1,
        "college_id": 1
    },
    {
        "id": 2,
        "firstname": "Suraj",
        "lastname": "Sharma",
        "M_name": "",
        "email": "surajaskmini@gmail.com",
        "major": "Computer",
        "address": "JNK",
        "phone_number": 9819692679,
        "person_id": 2,
        "college_id": 2
    },
    {
        "id": 3,
        "firstname": "Sushant",
        "lastname": "Kharel",
        "M_name": "Pauvaji",
        "email": "pauvaji@gmail.com",
        "major": "Computer",
        "address": "Chitwan",
        "phone_number": 9819898679,
        "person_id": 3,
        "college_id": 3
    },
    {
        "id": 4,
        "firstname": "Wusman",
        "lastname": "Khawaja",
        "M_name": "",
        "email": "wusman@gmail.com",
        "major": "Civil",
        "address": "Mars",
        "phone_number": 1234056789,
        "person_id": 5,
        "college_id": 4
    }
]